{
  "base_url": "https://www.stadtwerke-waiblingen.de/Privatkunden/Strom",
  "pages": [
    {
      "url": "https://www.stadtwerke-waiblingen.de/Privatkunden/Strom",
      "blocks": [
        {
          "heading": "Strom - von uns für Sie",
          "segments": [
            {
              "subheading": null,
              "text": "Ganz egal, ob man allein lebt, in einer WG oder im Mehrgenerationenhaus. Strom braucht man immer. Und diese Energie liefern wir genau so, wie sie gebraucht wird - zuverlässig und sicher.",
              "files": null,
              "contacts": null
            }
          ]
        },
        {
          "heading": "Unser breites Angebot für Sie",
          "segments": [
            {
              "subheading": "Ökostromtarif",
              "text": null,
              "files": null,
              "contacts": null
            },
            {
              "subheading": "Wärmestrom",
              "text": null,
              "files": null,
              "contacts": null
            },
            {
              "subheading": "Grundversorgung",
              "text": null,
              "files": null,
              "contacts": null
            },
            {
              "subheading": "Preisinformation",
              "text": null,
              "files": null,
              "contacts": null
            },
            {
              "subheading": "Stromkennzeichnung",
              "text": null,
              "files": null,
              "contacts": null
            }
          ]
        },
        {
          "heading": "Sie haben Fragen?",
          "segments": [
            {
              "subheading": "Wie setzt sich mein Strompreis zusammen?",
              "text": "Der Strompreis für einen Haushaltskunden in Deutschland setzt sich aus drei Hauptbestandteilen zusammen. Diese sind:\n\n1. der Preis für Energieerzeugung, Beschaffung und Lieferung\n2. der Preis für die Netznutzung und Messentgelt\n3. diverse Abgaben, Umlagen und Steuern (Konzessionsabgabe, Stromsteuer (im Volksmund: Ökosteuer), KWK-Umlage, EEG-Umlage, §19 StromNEV-Umlage (Umlage nach §19 Abs. 2 Stromnetzentgeltverordnung), Offshore-Haftungsumlage (nach dem Energiewirtschaftsgesetz EnWG, Novelle 2012), abLa-Umlage (Umlage für abschaltbare Lasten nach §18 AbLaV), Umsatzsteuer (Mehrwertsteuer). Mehr Informationen hierzu finden Sie auf der Seite \"Preisinformation\".",
              "files": null,
              "contacts": null
            },
            {
              "subheading": "Was ist die Stromsteuer?",
              "text": "Die Stromsteuer ist eine Abgabe, die an den Staat geht. Jeder Verbraucher zahlt die Stromsteuer pro verbrauchter Kilowattstunde.",
              "files": null,
              "contacts": null
            },
            {
              "subheading": "Was ist ein Netzbetreiber?",
              "text": "Netzbetreiber sind Versorgungsunternehmen, die Energie im Strom- oder Gasversorgungsnetz verteilen. Der Netzbetreiber ist gesetzlich für den ordnungsgemäßen Betrieb des Strom- oder Gasnetzes verantwortlich.",
              "files": null,
              "contacts": null
            },
            {
              "subheading": "Was ist eine Kilowattstunde (kWh)?",
              "text": "Die Kilowattstunde ist die Einheit für Energie. Mit der Bezeichnung Kilowattstunde wird der Verbrauch oder die Erzeugung von Energie gemessen. Beispielsweise kann eine 20-Watt-Energiesparlampe mit einer Kilowattstunde Strom 50 Stunden lang betrieben werden.",
              "files": null,
              "contacts": null
            },
            {
              "subheading": "Was ist der Verbrauchspreis?",
              "text": "Der Verbrauchspreis oder auch Arbeitspreis ist das Entgelt für die verbrauchte Strommenge. Er gibt an, wie viel jede verbrauchte Kilowattstunde (kWh) Strom kostet. Dieser beinhaltet sämtliche, mit dem Verbrauch zusammenhängende Kosten wie Beschaffungskosten, Netzentgelte, Konzessionsabgaben, staatliche Steuern und Abgaben.",
              "files": null,
              "contacts": null
            }
          ]
        }
      ]
    },
    {
      "url": "https://www.stadtwerke-waiblingen.de/Privatkunden/Strom/Preisinformation",
      "blocks": [
        {
          "heading": "Preisinformation",
          "segments": [
            {
              "subheading": null,
              "text": "Entwicklung der gesetzlichen Umlagen und Abgaben:",
              "files": null,
              "contacts": null
            },
            {
              "subheading": null,
              "text": null,
              "files": "Preisinformation table with years 2010 to 2026 and various charges in Ct/kWh",
              "contacts": null
            },
            {
              "subheading": "Erklärungen zu den Umlagen und Abgaben",
              "text": null,
              "files": null,
              "contacts": null
            },
            {
              "subheading": "Was ist die KWKG-Umlage?",
              "text": "KWK ist die Bezeichnung für Kraft-Wärme-Kopplung. Die KWKG-Umlage ist ein im Gesetz festgeschriebener Passus für Erhaltung, Modernisierung und Ausbau der Kraft-Wärme-Kopplung (KWKG), der dafür sorgt, dass die erhöhten Kosten der Betreiber von Blockheizkraftwerken durch Umlagen ausgeglichen werden.",
              "files": null,
              "contacts": null
            },
            {
              "subheading": "Was ist die Konzessionsabgabe?",
              "text": "Konzessionsabgaben müssen Energieversorgungsunternehmen und Wasserversorgungsunternehmen an die zuständigen Kommunen (Gemeinden/Städte) zahlen, damit sie von diesen das Recht erhalten, Kabel und Leitungen im Bereich der öffentlichen Straße und Wege zu verlegen.",
              "files": null,
              "contacts": null
            },
            {
              "subheading": "Was ist das Netznutzungsentgelt?",
              "text": "Das Netznutzungsentgelt ist von den Nutzern unseres Netzes zu entrichten, von den sog. Lieferanten. Diese Energielieferanten beliefern - ebenso wie wir - Kunden im Waiblinger Netzgebiet. Im Gegensatz zu den Stadtwerken Waiblingen sind sie jedoch weder für die Instandhaltung noch für die Tag- und Nacht-Rufbereitschaft bei Störungen für die Netze in Waiblingen zuständig. Hierfür fällt dieses Entgelt an.",
              "files": null,
              "contacts": null
            },
            {
              "subheading": "Was ist die EEG-Umlage?",
              "text": "Mit der EEG (Erneuerbare-Energien-Gesetz)-Umlage wird die Erzeugung von Strom aus erneuerbaren Energien gefördert. Die daraus entstehenden Mehrbelastungen werden bundesweit auf die Letztverbraucher umgelegt.",
              "files": null,
              "contacts": null
            },
            {
              "subheading": "Was ist die Offshore-Netzumlage?",
              "text": "Seit dem 01.01.2013 ist die Offshore-Netzumlage ein neuer Bestandteil des Strompreises für alle Endverbraucher von Strom. Wenn die Netzanbindung der Offshore-Windparks nicht funktioniert, entstehen Schadensersatzansprüche bei den jeweiligen Betreibern. Mit der Umlage unterstützen die Verbraucher die Übertragungsnetzbetreiber bei der Zahlung der entstandenen Kosten.",
              "files": null,
              "contacts": null
            },
            {
              "subheading": "Was ist die AbLaV?",
              "text": "AbLaV = Abschaltbare Lasten-Umlage ist eine Verordnung für kurzfristige Stromunterbrechungen bei Industriekunden und wird auf den Endverbraucher umgelegt. Sie ist im Strompreis enthalten. Ziel der AbLaV ist die Stabilisierung des Übertragungsnetzes und somit die Unternehmen zu belohnen, die schnell auf Zuruf ihren Verbrauch drosseln können.",
              "files": null,
              "contacts": null
            }
          ]
        },
        {
          "heading": "Kontakt",
          "segments": [
            {
              "subheading": "Kontakt allgemein",
              "text": null,
              "files": null,
              "contacts": "+49 7151 131-0"
            }
          ]
        },
        {
          "heading": "So erreichen Sie uns",
          "segments": [
            {
              "subheading": null,
              "text": "Schorndorfer Straße 67\n71332 Waiblingen",
              "files": null,
              "contacts": "07151 131-0"
            }
          ]
        }
      ]
    }
  ]
}